[
  {
    "id": "2019e26a-3b8f-4be1-b58c-1c753aec09d4",
    "checkin": "",
    "checkout": "",
    "title": "פוקט",
    "location": "Phuket, Thailand",
    "nights": 1,
    "duration": "הגעה / לילה ראשון",
    "transport": "רכב פרטי / מיניוואן",
    "status": "active",
    "x": 175,
    "y": 250,
    "notes": "לילה ראשון בפוקט. מומלץ לבחור מלון נוח ביחס לנקודת היציאה לקאו סוק למחרת.",
    "hasHotel": false,
    "hotelName": "",
    "bookingUrl": ""
  },
  {
    "id": "46cf3281-bd70-45c6-afc6-a233b70db482",
    "checkin": "",
    "checkout": "",
    "title": "פוקט → קאו סוק",
    "location": "Khao Sok National Park, Thailand",
    "nights": 2,
    "duration": "2.5–3.5 שעות",
    "transport": "רכב פרטי / מיניוואן",
    "status": "todo",
    "x": 250,
    "y": 145,
    "notes": "נסיעה ישירה מפוקט לקאו סוק. הכי נוח: הסעה פרטית או מיניוואן ישיר עד המלון / הכניסה לפארק.",
    "hasHotel": false,
    "hotelName": "",
    "bookingUrl": ""
  },
  {
    "id": "c72f85b6-ad70-4669-b615-33826ce810f7",
    "checkin": "",
    "checkout": "",
    "title": "קאו סוק → קו יאו נוי",
    "location": "Ko Yao Noi, Thailand",
    "nights": 0,
    "duration": "3–5 שעות כולל מעברים",
    "transport": "רכב + מעבורת",
    "status": "todo",
    "x": 300,
    "y": 230,
    "notes": "נסיעה מקאו סוק למזח באזור פאנג נגה / פוקט ואז מעבורת לקו יאו נוי. לבדוק שעות מעבורת מראש.",
    "hasHotel": false,
    "hotelName": "",
    "bookingUrl": ""
  },
  {
    "id": "c1db9d04-103e-4d15-a13f-e500d15fcb6b",
    "checkin": "",
    "checkout": "",
    "title": "קו יאו נוי → פוקט",
    "location": "Phuket, Thailand",
    "nights": 0,
    "duration": "1–1.5 שעות",
    "transport": "מעבורת + רכב",
    "status": "todo",
    "x": 175,
    "y": 250,
    "notes": "מעבורת חזרה מפייר בקו יאו נוי לפוקט ואז מונית / הסעה.",
    "hasHotel": false,
    "hotelName": "",
    "bookingUrl": ""
  },
  {
    "id": "5ecdc1a8-14f1-45c0-abb4-831a5163f823",
    "checkin": "",
    "checkout": "",
    "title": "פוקט → קוסמוי",
    "location": "Koh Samui, Thailand",
    "nights": 0,
    "duration": "כ־1–1.5 שעות טיסה ישירה",
    "transport": "טיסה",
    "status": "todo",
    "x": 585,
    "y": 185,
    "notes": "טיסה ישירה מפוקט לקוסמוי אם יש זמינות. כדאי להזמין מראש.",
    "hasHotel": false,
    "hotelName": "",
    "bookingUrl": ""
  },
  {
    "id": "cd2d6c13-62d7-47cc-8aac-7047dda86ec7",
    "checkin": "",
    "checkout": "",
    "title": "קוסמוי → קופנגן",
    "location": "Koh Phangan, Thailand",
    "nights": 0,
    "duration": "30–60 דקות",
    "transport": "מעבורת",
    "status": "todo",
    "x": 615,
    "y": 145,
    "notes": "מעבורת מקוסמוי לקופנגן.",
    "hasHotel": false,
    "hotelName": "",
    "bookingUrl": ""
  },
  {
    "id": "7635c940-d8af-4793-afbd-50fb15db26f0",
    "checkin": "",
    "checkout": "",
    "title": "קופנגן → קו טאו",
    "location": "Koh Tao, Thailand",
    "nights": 0,
    "duration": "60–90 דקות",
    "transport": "מעבורת",
    "status": "todo",
    "x": 650,
    "y": 95,
    "notes": "מעבורת לקו טאו. להשאיר מרווח כי הים עלול להשפיע.",
    "hasHotel": false,
    "hotelName": "",
    "bookingUrl": ""
  },
  {
    "id": "9acb115b-4eda-48b5-a4b4-810e0efe8892",
    "checkin": "",
    "checkout": "",
    "title": "קו טאו → קופנגן",
    "location": "Koh Phangan, Thailand",
    "nights": 0,
    "duration": "60–90 דקות",
    "transport": "מעבורת",
    "status": "todo",
    "x": 615,
    "y": 145,
    "notes": "חזרה מקו טאו לקופנגן.",
    "hasHotel": false,
    "hotelName": "",
    "bookingUrl": ""
  },
  {
    "id": "65f31964-a54a-4426-9898-52af285ee303",
    "checkin": "",
    "checkout": "",
    "title": "קופנגן → פוקט",
    "location": "Phuket, Thailand",
    "nights": 0,
    "duration": "כ־6–9 שעות",
    "transport": "מעבורת + רכב",
    "status": "todo",
    "x": 175,
    "y": 250,
    "notes": "מעבורת לסוראט תאני ומשם רכב / מיניוואן לפוקט. חלופה: קופנגן → קוסמוי → טיסה לפוקט.",
    "hasHotel": false,
    "hotelName": "",
    "bookingUrl": ""
  }
]
